xsugar/__init__.py
xsugar/conftest.py
xsugar/examples/examples.py
xsugar/source/conditions.py
xsugar/source/experiments.py
xsugar/source/processing.py
xsugar/test/__init__.py
xsugar/test/conftest.py
xsugar/test/shorthand.py
xsugar/test/test_averaging.py
xsugar/test/test_conditions.py
xsugar/test/test_directories.py
xsugar/test/test_execution.py
xsugar/test/test_figures.py
xsugar/test/test_grouping.py
xsugar/test/test_load_data.py
xsugar/test/test_master_data.py
xsugar/test/test_names.py
xsugar/test/test_photocurrent.py
xsugar/test/test_save_data.py
xsugar/test/test_units.py
xsugar/test/data/data/test/REFL2/REFL2~material=AlN~modulation_voltage=0V~spectra=R0.csv
xsugar/test/data/data/test/REFL2/REFL2~material=AlN~modulation_voltage=10V~spectra=deltaR.csv
xsugar/test/data/data/test/REFL2/REFL2~material=AlN~modulation_voltage=20V~spectra=deltaR.csv
xsugar/test/data/data/test/REFL2/REFL2~material=Al~modulation_voltage=0V~spectra=R0.csv
xsugar/test/data/data/test/REFL2/REFL2~material=Au~modulation_voltage=0V~spectra=R0.csv
xsugar/test/data/data/test/TEST1/TEST1~wafer=1~type=locked_coupled~peak=Si.txt
xsugar-0.1.29.dist-info/LICENSE.txt
xsugar-0.1.29.dist-info/METADATA
xsugar-0.1.29.dist-info/WHEEL
xsugar-0.1.29.dist-info/top_level.txt
xsugar-0.1.29.dist-info/RECORD
