Metadata-Version: 2.1
Name: xsugar
Version: 0.1.29
Summary: Experimental design, data analysis, and plotting framework in python
Home-page: https://github.com/edmundsj/xsugar
Author: Jordan Edmunds
Author-email: edmundsj@uci.edu
License: MIT
Platform: UNKNOWN
Classifier: Programming Language :: Python :: 3
Classifier: License :: OSI Approved :: MIT License
Classifier: Operating System :: OS Independent
Requires-Python: >=3.6
Requires-Dist: numpy (>=1.14.5)
Requires-Dist: matplotlib (>=2.0.0)
Requires-Dist: pandas (>=0.24.0)
Requires-Dist: scipy (>=1.2.2)
Requires-Dist: pyyaml (>=5.1.1)
Requires-Dist: pint (>=0.16.0)
Requires-Dist: sugarplot
Requires-Dist: spectralpy
Requires-Dist: sciparse
Requires-Dist: liapy
